pycyclebio/__init__.py
pycyclebio/fitting.py
pycyclebio-1.0.7.dist-info/METADATA
pycyclebio-1.0.7.dist-info/WHEEL
pycyclebio-1.0.7.dist-info/top_level.txt
pycyclebio-1.0.7.dist-info/RECORD
