Metadata-Version: 2.4
Name: pycyclebio
Version: 1.0.7
Summary: Python based toolkit for temporal molecular biology
Author-email: Alexander R Bennett <alex.bennett@gu.se>
License: MIT
Project-URL: Homepage, https://github.com/Glycocalex/PyCycle
Project-URL: Issues, https://github.com/Glycocalex/PyCycle/issues
Classifier: Programming Language :: Python :: 3
Classifier: Operating System :: OS Independent
Requires-Python: >=3.8
Requires-Dist: scipy
Requires-Dist: statsmodels
Requires-Dist: pandas
Requires-Dist: numpy
